CHANGES
MANIFEST.in
README
setup.py
jobprogress/__init__.py
jobprogress/job.py
jobprogress/performer.py
jobprogress/qt.py
jobprogress.egg-info/PKG-INFO
jobprogress.egg-info/SOURCES.txt
jobprogress.egg-info/dependency_links.txt
jobprogress.egg-info/top_level.txt