Metadata-Version: 1.1
Name: jobprogress
Version: 1.0.4
Summary: Cross-toolkit UI progress tracking
Home-page: http://hg.hardcoded.net/jobprogress/
Author: Hardcoded Software
Author-email: hsoft@hardcoded.net
License: BSD License
Platform: UNKNOWN
Classifier: Development Status :: 5 - Production/Stable
Classifier: Intended Audience :: Developers
Classifier: License :: OSI Approved :: BSD License
Classifier: Programming Language :: Python :: 3
